reg/__init__.py
reg/regi.py
my_unique_reg_package-1.3.dist-info/LICENCE.txt
my_unique_reg_package-1.3.dist-info/METADATA
my_unique_reg_package-1.3.dist-info/WHEEL
my_unique_reg_package-1.3.dist-info/top_level.txt
my_unique_reg_package-1.3.dist-info/RECORD
