Metadata-Version: 2.1
Name: my-unique-reg-package
Version: 1.3
Summary: Different Types of Regression
Author: Sahraoui Tarek Ziad
Author-email: tziad2027@gmail.com
License-File: LICENCE.txt
